packaging_demo/__init__.py
packaging_demo/slow.py
packaging_demo/states_capital.json
packaging_demo/states_info.py
packaging_demo/folder/__init__.py
packaging_demo/folder/nested_folder/__init__.py
packaging_demo/folder/nested_folder/nested_module.py
packaging_demo_abhi-0.0.6.dist-info/METADATA
packaging_demo_abhi-0.0.6.dist-info/WHEEL
packaging_demo_abhi-0.0.6.dist-info/top_level.txt
packaging_demo_abhi-0.0.6.dist-info/RECORD
